bincfg/__init__.py
bincfg/cfg/__init__.py
bincfg/cfg/cfg.py
bincfg/cfg/cfg_basic_block.py
bincfg/cfg/cfg_dataset.py
bincfg/cfg/cfg_edge.py
bincfg/cfg/cfg_function.py
bincfg/cfg/cfg_parsers.py
bincfg/cfg/mem_cfg.py
bincfg/cfg/mem_cfg_dataset.py
bincfg/normalization/__init__.py
bincfg/normalization/base_normalizer.py
bincfg/normalization/base_tokenizer.py
bincfg/normalization/libc_func_names.py
bincfg/normalization/multi_normalizer.py
bincfg/normalization/norm_funcs.py
bincfg/normalization/norm_utils.py
bincfg/normalization/normalize.py
bincfg/normalization/java/__init__.py
bincfg/normalization/java/java_normalizers.py
bincfg/normalization/java/java_tokenizer.py
bincfg/normalization/x86/__init__.py
bincfg/normalization/x86/x86_norm_funcs.py
bincfg/normalization/x86/x86_normalizers.py
bincfg/normalization/x86/x86_tokenizer.py
bincfg/utils/__init__.py
bincfg/utils/atomic_token_dict.py
bincfg/utils/cfg_utils.py
bincfg/utils/misc_utils.py
bincfg/utils/type_utils.py
bincfg-1.0.2.dist-info/LICENSE
bincfg-1.0.2.dist-info/METADATA
bincfg-1.0.2.dist-info/WHEEL
bincfg-1.0.2.dist-info/top_level.txt
bincfg-1.0.2.dist-info/RECORD
